insee_number_translator/__init__.py
insee_number_translator/data/__init__.py
insee_number_translator/data/cities.py
insee_number_translator/data/countries.py
insee_number_translator/data/departments.py
insee_number_translator/main.py
insee_number_translator-0.3.1.dist-info/entry_points.txt
insee_number_translator-0.3.1.dist-info/LICENSE
insee_number_translator-0.3.1.dist-info/WHEEL
insee_number_translator-0.3.1.dist-info/METADATA
insee_number_translator-0.3.1.dist-info/RECORD
