Metadata-Version: 2.1
Name: insee-number-translator
Version: 0.3.1
Summary: Translate french INSEE number to meaningful data
Home-page: https://git.augendre.info/gaugendre/insee_number_translator
License: MIT
Author: Gabriel Augendre
Author-email: gabriel@augendre.info
Requires-Python: >=3.7,<4.0
Classifier: License :: OSI Approved :: MIT License
Classifier: Programming Language :: Python :: 3
Classifier: Programming Language :: Python :: 3.7
Classifier: Programming Language :: Python :: 3.8
Classifier: Programming Language :: Python :: 3.9
Project-URL: Repository, https://git.augendre.info/gaugendre/insee_number_translator
